yandex_query_magic/__init__.py
yandex_query_magic/ipythondisplay.py
yandex_query_magic/jinja_template.py
yandex_query_magic/magics.py
yandex_query_magic/main.py
yandex_query_magic/query_results.py
yandex_query_magic/sqltext_parser.py
yandex_query_magic-0.2.dist-info/METADATA
yandex_query_magic-0.2.dist-info/WHEEL
yandex_query_magic-0.2.dist-info/licenses/LICENSE.md
yandex_query_magic-0.2.dist-info/RECORD
