Metadata-Version: 2.1
Name: yandex-query-magic
Version: 0.2
Summary: The Yandex Query official Jupyter Notebook plugin
Project-URL: Homepage, https://github.com/yandex-cloud/yandex-query-magics
Project-URL: Issues, https://github.com/yandex-cloud/yandex-query-magics/issues
Author-email: cloud@support.yandex.ru
License-Expression: MIT
License-File: LICENSE.md
Classifier: License :: OSI Approved :: MIT License
Classifier: Operating System :: OS Independent
Classifier: Programming Language :: Python :: 3
Requires-Python: >=3.10
Requires-Dist: aiohttp-retry>=2.8.3
Requires-Dist: aiohttp>=3.9.1
Requires-Dist: asyncio>=3.4.3
Requires-Dist: cryptography>=3.4.8
Requires-Dist: ipywidgets>=8.1.1
Requires-Dist: jupyter-contrib-nbextensions>=0.7.0
Requires-Dist: jupyter-ui-poll>=0.2.2
Requires-Dist: nest-asyncio>=1.6.0
Requires-Dist: pandas>=2.2.0
Requires-Dist: pyjwt>=2.3.0
Requires-Dist: python-dateutil>=2.8.2
Requires-Dist: requests>=2.31.0
Requires-Dist: typing>=3.7.4.3
Requires-Dist: urllib3>=1.26.5
Provides-Extra: test
Requires-Dist: jinja2; extra == 'test'
Requires-Dist: pytest-asyncio>=0.23.4; extra == 'test'
Requires-Dist: pytest-httpserver>=1.0.8; extra == 'test'
Requires-Dist: pytest>=7.4.4; extra == 'test'
Requires-Dist: werkzeug>=3.0.1; extra == 'test'
